dirorganizer/__init__.py
dirorganizer/arrange_files.py
dirorganizer-1.0.4.dist-info/METADATA
dirorganizer-1.0.4.dist-info/WHEEL
dirorganizer-1.0.4.dist-info/entry_points.txt
dirorganizer-1.0.4.dist-info/top_level.txt
dirorganizer-1.0.4.dist-info/RECORD
