Metadata-Version: 2.4
Name: dirorganizer
Version: 1.0.4
Summary: A simple CLI tool to organize files by extensions
Home-page: https://github.com/SudoRV/fileorganizer
Author: Rahul Verma
Author-email: rahulverma.1.2005@gamil.com
Classifier: Programming Language :: Python :: 3
Classifier: License :: OSI Approved :: MIT License
Classifier: Operating System :: OS Independent
Requires-Python: >=3.6
Dynamic: author
Dynamic: author-email
Dynamic: classifier
Dynamic: description
Dynamic: description-content-type
Dynamic: home-page
Dynamic: requires-python
Dynamic: summary
